jtorch_utils/constants.py
jtorch_utils/datasets.py
jtorch_utils/train.py
jtorch_utils-0.1.2.dist-info/METADATA
jtorch_utils-0.1.2.dist-info/WHEEL
jtorch_utils-0.1.2.dist-info/RECORD
