Metadata-Version: 2.1
Name: jtorch-utils
Version: 0.1.2
Summary: Tools for PyTorch model development and experimentation.
License: MIT
Author: Johannes Traa
Requires-Python: >=3.11.5,<4.0.0
Classifier: License :: OSI Approved :: MIT License
Classifier: Programming Language :: Python :: 3
Requires-Dist: pandas (>=2.0.3,<3.0.0)
